stats/Stats.py
stats/__init__.py
counter_stats-0.0.2.dist-info/LICENSE
counter_stats-0.0.2.dist-info/METADATA
counter_stats-0.0.2.dist-info/WHEEL
counter_stats-0.0.2.dist-info/top_level.txt
counter_stats-0.0.2.dist-info/RECORD
