Metadata-Version: 2.1
Name: counter-stats
Version: 0.0.2
Summary: Python module for various Counter classes
Home-page: https://github.com/alpaalpa/counter-stats
Author: Albert Pang
Author-email: alpaaccount@mac.com
Project-URL: Bug Tracker, https://github.com/alpaalpa/counter-stats/issues
Classifier: Programming Language :: Python :: 3
Classifier: License :: OSI Approved :: MIT License
Classifier: Operating System :: OS Independent
Requires-Python: >=3.8
License-File: LICENSE
Requires-Dist: munch
